[
    {
      "id":"1",
      "priceRange":"1727",
      "brandName": "Samsung Galaxy S20 Ultra 5G",
      "OS":"Android",
      "cameraDayScore": "128",
      "cameraNightScore": "56",
      "cameraSelfieScore": "100",
      "cameraVideoScore": "106",
      "cameraZoomScore": "88",
      "batteryScore": "87",
      "audioPlaybackQualityScore": "71",
      "audioRecordingQualityScore": "65",
      "displayScore": "87",
      "performanceScore": "41.6",
      "image": "Samsung_Galaxy_S20_Ultra.jpg"
    },
    {
      "id":"2",
      "priceRange":"1090",
      "brandName": "Apple iPhone 12",
      "OS":"iOS",
      "cameraDayScore": "132",
      "cameraNightScore": "59",
      "cameraSelfieScore": "98",
      "cameraVideoScore": "106",
      "cameraZoomScore": "41",
      "batteryScore": "84",
      "audioPlaybackQualityScore": "73",
      "audioRecordingQualityScore": "73",
      "displayScore": "85",
      "performanceScore": "56.7",
      "image":"iPhone-12.png"
    },
    {
      "id":"3",
      "priceRange":"1240",
      "brandName": "Apple iPhone 12 Pro",
      "OS":"iOS",
      "cameraDayScore": "135",
      "cameraNightScore": "59",
      "cameraSelfieScore": "98",
      "cameraVideoScore": "112",
      "cameraZoomScore": "66",
      "batteryScore": "81",
      "audioPlaybackQualityScore": "73",
      "audioRecordingQualityScore": "73",
      "displayScore": "87",
      "performanceScore": "59.6",
      "image": "iPhone-12.png"
    },
    {
      "id":"4",
      "priceRange":"970",
      "brandName": "Apple iPhone 12 mini",
      "OS":"iOS",
      "cameraDayScore": "132",
      "cameraNightScore": "59",
      "cameraSelfieScore": "98",
      "cameraVideoScore": "112",
      "cameraZoomScore": "41",
      "batteryScore": "69",
      "audioPlaybackQualityScore": "73",
      "audioRecordingQualityScore": "73",
      "displayScore": "85",
      "performanceScore": "59",
      "image": ""
    },
    {
      "id":"5",
      "priceRange":"460",
      "brandName": "Samsung Galaxy A52 5G",
      "OS":"Android",
      "cameraDayScore": "102",
      "cameraNightScore": "21",
      "cameraSelfieScore": "",
      "cameraVideoScore": "90",
      "cameraZoomScore": "56",
      "batteryScore": "111",
      "audioPlaybackQualityScore": "71",
      "audioRecordingQualityScore": "63",
      "displayScore": "79",
      "performanceScore": "38.6",
      "image": ""
    }
  ]